[
 {
   "Titre": "T1",
   "Perte d'activité au quatrième trimestre 2020 (en %)": -10,
   "Perte d'activité au premier trimestre 2021 (en %)": -6
 },
 {
   "Titre": "T2",
   "Perte d'activité au quatrième trimestre 2020 (en %)": -8,
   "Perte d'activité au premier trimestre 2021 (en %)": -5
 },
 {
   "Titre": "T3",
   "Perte d'activité au quatrième trimestre 2020 (en %)": -8,
   "Perte d'activité au premier trimestre 2021 (en %)": -6
 },
 {
   "Titre": "T4",
   "Perte d'activité au quatrième trimestre 2020 (en %)": -8,
   "Perte d'activité au premier trimestre 2021 (en %)": -5
 },
 {
   "Titre": "T5",
   "Perte d'activité au quatrième trimestre 2020 (en %)": -9,
   "Perte d'activité au premier trimestre 2021 (en %)": -5
 },
 {
   "Titre": "T6",
   "Perte d'activité au quatrième trimestre 2020 (en %)": -9,
   "Perte d'activité au premier trimestre 2021 (en %)": -6
 },
 {
   "Titre": "T7",
   "Perte d'activité au quatrième trimestre 2020 (en %)": -10,
   "Perte d'activité au premier trimestre 2021 (en %)": -6
 },
 {
   "Titre": "T8",
   "Perte d'activité au quatrième trimestre 2020 (en %)": -8,
   "Perte d'activité au premier trimestre 2021 (en %)": -5
 },
 {
   "Titre": "T9",
   "Perte d'activité au quatrième trimestre 2020 (en %)": -8,
   "Perte d'activité au premier trimestre 2021 (en %)": -5
 },
 {
   "Titre": "T10",
   "Perte d'activité au quatrième trimestre 2020 (en %)": -8,
   "Perte d'activité au premier trimestre 2021 (en %)": -5
 },
 {
   "Titre": "T11",
   "Perte d'activité au quatrième trimestre 2020 (en %)": -8,
   "Perte d'activité au premier trimestre 2021 (en %)": -5
 },
 {
   "Titre": "T12",
   "Perte d'activité au quatrième trimestre 2020 (en %)": -9,
   "Perte d'activité au premier trimestre 2021 (en %)": -5
 }
]
